greenreq/__init__.py
greenreq/green_requests.so
greenreq-0.1.2.dist-info/LICENSE
greenreq-0.1.2.dist-info/METADATA
greenreq-0.1.2.dist-info/WHEEL
greenreq-0.1.2.dist-info/top_level.txt
greenreq-0.1.2.dist-info/RECORD
