Metadata-Version: 2.1
Name: greenreq
Version: 0.1.2
Summary: A Python package for making HTTP requests
Home-page: https://github.com/mr-green-143/greenreq
Author: Tamim Ahmed
Author-email: admin@teamgreenxd.com
License: MIT
Classifier: Programming Language :: Python :: 3
Classifier: License :: OSI Approved :: MIT License
Classifier: Operating System :: OS Independent
Requires-Python: >=3.6
License-File: LICENSE
